emoi/__init__.py
emoi/cli.py
emoi-1.0.3.dist-info/METADATA
emoi-1.0.3.dist-info/WHEEL
emoi-1.0.3.dist-info/entry_points.txt
emoi-1.0.3.dist-info/top_level.txt
emoi-1.0.3.dist-info/RECORD
