Metadata-Version: 2.1
Name: emoi
Version: 1.0.3
Summary: emoi
Home-page: https://trobz.com
Author: Trobz
Author-email: contact@trobz.com
License: MIT
Platform: UNKNOWN
Classifier: Intended Audience :: Developers
Classifier: Development Status :: 5 - Production/Stable
Classifier: License :: OSI Approved :: MIT License
Classifier: Operating System :: OS Independent
Classifier: Programming Language :: Python
Classifier: Programming Language :: Python :: 2
Classifier: Programming Language :: Python :: 3
Classifier: Environment :: Console
Classifier: Topic :: Software Development
Requires-Dist: click (>=7)
Requires-Dist: trobz
